popsicle.so
popsicle-0.9.6.dist-info/RECORD
popsicle-0.9.6.dist-info/LICENSE
popsicle-0.9.6.dist-info/WHEEL
popsicle-0.9.6.dist-info/LICENSE.COMMERCIAL
popsicle-0.9.6.dist-info/top_level.txt
popsicle-0.9.6.dist-info/METADATA
popsicle-0.9.6.dist-info/LICENSE.GPLv3
popsicle/Colours.pyi
popsicle/__init__.pyi
