Metadata-Version: 2.1
Name: popsicle
Version: 0.9.6
Summary: popsicle: Python integration for JUCE with pybind11.
Home-page: https://github.com/kunitoki/popsicle
Author: kunitoki
Author-email: kunitoki@gmail.com
License: GPLv3
Platform: macosx
Platform: win32
Platform: linux
Classifier: Intended Audience :: Developers
Classifier: Development Status :: 4 - Beta
Classifier: Topic :: Software Development :: Libraries :: Application Frameworks
Classifier: License :: Other/Proprietary License
Classifier: License :: OSI Approved :: GNU General Public License v3 (GPLv3)
Classifier: Programming Language :: C++
Classifier: Programming Language :: Python
Classifier: Programming Language :: Python :: 3.10
Classifier: Programming Language :: Python :: 3.11
Classifier: Programming Language :: Python :: 3.12
Classifier: Operating System :: MacOS :: MacOS X
Classifier: Operating System :: Microsoft :: Windows
Classifier: Operating System :: POSIX :: Linux
Requires-Python: >=3.10
License-File: LICENSE
License-File: LICENSE.COMMERCIAL
License-File: LICENSE.GPLv3
